{
  "header": {
    "logo": {
      "text": "Uralliance",
      "href": "/"
    },
    "items": [
      {
        "label": "Главная",
        "href": "/",
        "category": "general"
      },
      {
        "label": "Юридические услуги",
        "href": "/services/legal",
        "category": "legal",
        "icon": "Scale",
        "hasDropdown": true,
        "dropdownItems": [
          {
            "label": "ЭЦП и Рутокен",
            "description": "Электронные подписи для бизнеса",
            "href": "/ecp",
            "icon": "KeyRound"
          },
          {
            "label": "Такском ЭДО",
            "description": "Отчётность и документооборот",
            "href": "/edo",
            "icon": "FileText"
          },
          {
            "label": "Федресурс",
            "description": "Публикации о ликвидации и банкротстве",
            "href": "/fedresurs",
            "icon": "Globe"
          },
          {
            "label": "Ликвидация организаций",
            "description": "Добровольная и упрощённая ликвидация",
            "href": "/liquidation",
            "icon": "FileX"
          },
          {
            "label": "Реорганизация",
            "description": "Слияние, присоединение, разделение",
            "href": "/services/legal/reorganization",
            "icon": "GitMerge"
          },
          {
            "label": "Регистрация бизнеса",
            "description": "Регистрация ООО, ИП, работа с налоговой",
            "href": "/services/legal/corporate",
            "icon": "Building2"
          },
          {
            "label": "Бухгалтерский аутсорсинг",
            "description": "Ведение учёта, сдача отчётности",
            "href": "/services/legal/accounting",
            "icon": "Calculator"
          }
        ]
      },
      {
        "label": "IT-решения",
        "href": "/services/tech",
        "category": "tech",
        "icon": "Code",
        "hasDropdown": true,
        "dropdownItems": [
          {
            "label": "Сайты и веб-приложения",
            "description": "Сайты, личные кабинеты, магазины",
            "href": "/services/tech/web",
            "icon": "Globe"
          },
          {
            "label": "Чат-боты",
            "description": "Telegram, WhatsApp, автоматизация",
            "href": "/services/tech/bots",
            "icon": "MessageSquare"
          },
          {
            "label": "Боты для MAX",
            "description": "Российский мессенджер, Mini Apps",
            "href": "/max",
            "icon": "Bot"
          },
          {
            "label": "Интеграции с 1С",
            "description": "Обмен данными между системами",
            "href": "/services/tech/crm",
            "icon": "Workflow"
          },
          {
            "label": "AI и автоматизация",
            "description": "Умные помощники и обработка данных",
            "href": "/services/tech/ai",
            "icon": "Sparkles"
          }
        ]
      },
      {
        "label": "Прайс",
        "href": "/price",
        "category": "general"
      },
      {
        "label": "О компании",
        "href": "/about",
        "category": "general"
      },
      {
        "label": "Контакты",
        "href": "/contacts",
        "category": "general"
      }
    ],
    "ctaButtons": [
      {
        "label": "Legal",
        "href": "/services/legal",
        "variant": "outline-legal"
      },
      {
        "label": "Tech",
        "href": "/services/tech",
        "variant": "primary-tech"
      }
    ]
  },
  "footer": {
    "tagline": "Юральянс — юристы и программисты во Владивостоке. Защищаем и ускоряем ваш бизнес.",
    "copyright": "ООО «Юральянс» (Uralliance). Все права защищены.",
    "columns": [
      {
        "title": "Юридические услуги",
        "category": "legal",
        "links": [
          {
            "label": "ЭЦП и Рутокен",
            "href": "/ecp"
          },
          {
            "label": "Такском ЭДО",
            "href": "/edo"
          },
          {
            "label": "Ликвидация организаций",
            "href": "/liquidation"
          },
          {
            "label": "Реорганизация",
            "href": "/services/legal/reorganization"
          },
          {
            "label": "Регистрация бизнеса",
            "href": "/services/legal/corporate"
          },
          {
            "label": "Бухгалтерский аутсорсинг",
            "href": "/services/legal/accounting"
          },
          {
            "label": "Федресурс",
            "href": "/fedresurs"
          }
        ]
      },
      {
        "title": "IT-решения",
        "category": "tech",
        "links": [
          {
            "label": "Сайты и веб-приложения",
            "href": "/services/tech/web"
          },
          {
            "label": "Чат-боты",
            "href": "/services/tech/bots"
          },
          {
            "label": "Боты для MAX",
            "href": "/max"
          },
          {
            "label": "Интеграции с 1С",
            "href": "/services/tech/crm"
          },
          {
            "label": "AI и автоматизация",
            "href": "/services/tech/ai"
          }
        ]
      },
      {
        "title": "Компания",
        "category": "general",
        "links": [
          {
            "label": "О нас",
            "href": "/about"
          },
          {
            "label": "Прайс",
            "href": "/price"
          },
          {
            "label": "Контакты",
            "href": "/contacts"
          }
        ]
      }
    ],
    "legal": [
      {
        "label": "Политика конфиденциальности",
        "href": "/privacy"
      },
      {
        "label": "Условия использования",
        "href": "/terms"
      }
    ]
  },
  "mobile": {
    "menuTitle": "Меню",
    "contactHint": "Свяжитесь с нами:",
    "ctaButtons": [
      {
        "label": "Юридические услуги",
        "href": "/services/legal",
        "variant": "outline-legal"
      },
      {
        "label": "IT-решения",
        "href": "/services/tech",
        "variant": "primary-tech"
      }
    ]
  },
  "breadcrumbs": {
    "home": "Главная",
    "separator": "/"
  }
}
